llama_index/tools/brave_search/__init__.py
llama_index/tools/brave_search/base.py
llama_index_tools_brave_search-0.4.1.dist-info/METADATA
llama_index_tools_brave_search-0.4.1.dist-info/WHEEL
llama_index_tools_brave_search-0.4.1.dist-info/licenses/LICENSE
llama_index_tools_brave_search-0.4.1.dist-info/RECORD
